spots_in_yeasts/__init__.py
spots_in_yeasts/_reader.py
spots_in_yeasts/_widget.py
spots_in_yeasts/formatData.py
spots_in_yeasts/napari.yaml
spots_in_yeasts/siy-convert-format.py
spots_in_yeasts/spotsInYeasts.py
spots_in_yeasts/test-nuclei.py
spots_in_yeasts/_tests/__init__.py
spots_in_yeasts/_tests/test_spot_in_yeasts.py
spots_in_yeasts/_tests/test_widgets.py
spots_in_yeasts-1.2.0.dist-info/LICENSE
spots_in_yeasts-1.2.0.dist-info/METADATA
spots_in_yeasts-1.2.0.dist-info/WHEEL
spots_in_yeasts-1.2.0.dist-info/entry_points.txt
spots_in_yeasts-1.2.0.dist-info/top_level.txt
spots_in_yeasts-1.2.0.dist-info/RECORD
