Metadata-Version: 2.1
Name: spots-in-yeasts
Version: 1.2.0
Summary: A Napari plugin segmenting yeast cells and fluo spots to extract statistics.
Home-page: https://github.com/MontpellierRessourcesImagerie/spots-in-yeasts
Author: Clément H. Benedetti
Author-email: clement.benedetti@mri.cnrs.fr
License: MIT
Project-URL: Bug Tracker, https://github.com/MontpellierRessourcesImagerie/spots-in-yeasts/issues
Project-URL: Documentation, https://github.com/MontpellierRessourcesImagerie/spots-in-yeasts#README.md
Project-URL: Source Code, https://github.com/MontpellierRessourcesImagerie/spots-in-yeasts
Project-URL: User Support, https://github.com/MontpellierRessourcesImagerie/spots-in-yeasts/issues
Classifier: Development Status :: 2 - Pre-Alpha
Classifier: Framework :: napari
Classifier: Intended Audience :: Developers
Classifier: License :: OSI Approved :: MIT License
Classifier: Operating System :: OS Independent
Classifier: Programming Language :: Python
Classifier: Programming Language :: Python :: 3
Classifier: Programming Language :: Python :: 3 :: Only
Classifier: Programming Language :: Python :: 3.8
Classifier: Programming Language :: Python :: 3.9
Classifier: Programming Language :: Python :: 3.10
Classifier: Topic :: Scientific/Engineering :: Image Processing
Requires-Python: >=3.8
License-File: LICENSE
Requires-Dist: numpy
Requires-Dist: magicgui
Requires-Dist: magic-class
Requires-Dist: qtpy
Requires-Dist: opencv-python
Requires-Dist: matplotlib
Requires-Dist: termcolor
Requires-Dist: scikit-image
Requires-Dist: tifffile
Requires-Dist: cellpose
Requires-Dist: napari
Provides-Extra: testing
Requires-Dist: tox ; extra == 'testing'
Requires-Dist: pytest ; extra == 'testing'
Requires-Dist: pytest-cov ; extra == 'testing'
Requires-Dist: pytest-qt ; extra == 'testing'
Requires-Dist: napari ; extra == 'testing'
Requires-Dist: pyqt5 ; extra == 'testing'
